{
  "cyclone": {
    "name": "ARTHUR",
    "category": "Tropical Storm",
    "current_location": "about 210 miles SSW of Cape Hatteras, North Carolina",
    "coordinates": "32.4N, 76.9W",
    "motion": {
      "direction": "NNE",
      "speed": "10 mph"
    },
    "trajectory": "Moving north-northeast, forecast to skirt the North Carolina Outer Banks Monday, then accelerate northeast and turn east away from the mid-Atlantic coast",
    "expected_landfall_location": "near or just east of Cape Hatteras, NC (brush rather than a direct landfall)",
    "expected_landfall_date": "2020-05-18",
    "hours_to_landfall": "12",
    "hours_to_offshore": "24",
    "hours_of_strike": "12"
  },
  "port": {
    "name": "South Jersey Port Corp, NJ"
  },
  "weather_observation": {
    "within_uncertainty_cone": "No",
    "forecast_window": "5",
    "under_watch": "None",
    "under_warning": "None",
    "watch_coast": "Surf City to Duck NC, including Pamlico and Albemarle Sounds",
    "warning_coast": "Surf City to Duck NC, including Pamlico and Albemarle Sounds (Tropical Storm Warning)",
    "impacted_coast": "Southeast U.S. through mid-Atlantic coastline from Georgia to New Jersey with rough surf and rip currents",
    "expected_closest_date_to_port": "2020-05-19",
    "expected_leaving_port_date": "2020-05-19",
    "closest_wind_data_location": "CAPE HENLOPEN",
    "culmulative_wind_34kt": "7%",
    "culmulative_wind_50kt": "0%",
    "34kt_max": "7%",
    "time_to_34kt_max": "48",
    "time_to_34kt_non_zero": "12",
    "time_to_50kt_max": "0",
    "gale_probability": {
      "in 12h": "3%",
      "in 24h": "5%",
      "in 48h": "7%",
      "in 72h": "7%",
      "in 96h": "7%"
    },
    "first_hazard": "Start of heavy rainfall",
    "rain_fall_above_4_inch": "No",
    "storm_surge_above_3_feet": "No",
    "wind": "Gusty east to northeast winds 25–35 mph possible early Tuesday as Arthur passes offshore",
    "storm_surge": "Minor tidal enhancement and dangerous rip currents possible, but surge heights below 3 ft",
    "rainfall": "1–2 inches of rain possible Tuesday with locally higher amounts in bands",
    "other_hazards": "High surf and rip currents could disrupt vessel movements and port approaches"
  }
}