{
  "cyclone": {
    "name": "DELTA",
    "category": "Category 2",
    "current_location": "about 35 mi (55 km) W of Cancún, Mexico",
    "coordinates": "21.1N, 87.4W",
    "motion": {
      "direction": "NW",
      "speed": "17 mph"
    },
    "trajectory": "moving northwest across the southern Gulf of Mexico, then turning north toward the Louisiana coast while remaining well east of the Texas Coastal Bend",
    "expected_landfall_location": "south-central Louisiana coast (near Morgan City/Cameron area)",
    "expected_landfall_date": "2020-10-09",
    "hours_to_landfall": "60",
    "hours_to_offshore": "0", 
    "hours_of_strike": "0"
  },
  "port": {
    "name": "Corpus Christi, TX"
  },
  "weather_observation": {
    "within_uncertainty_cone": "No",
    "forecast_window": "5",
    "under_watch": "None",
    "under_warning": "None",
    "watch_coast": "None",
    "warning_coast": "None",
    "impacted_coast": "Greatest impacts expected from upper Texas coast eastward across Louisiana, Mississippi and Alabama coasts",
    "expected_closest_date_to_port": "2020-10-08",
    "expected_leaving_port_date": "2020-10-10",
    "closest_wind_data_location": "CORPUS CHRISTI TX",
    "culmulative_wind_34kt": "6%",
    "culmulative_wind_50kt": "0%",
    "34kt_max": "3%",
    "time_to_34kt_max": "72",
    "time_to_34kt_non_zero": "36",
    "time_to_50kt_max": "N/A",
    "gale_probability": {
      "in 12h": "0%",
      "in 24h": "0%",
      "in 48h": "2%",
      "in 72h": "3%",
      "in 96h": "0%"
    },
    "first_hazard": "Start of heavy rainfall",
    "rain_fall_above_4_inch": "Unlikely (forecast totals 1–2 inches)",
    "storm_surge_above_3_feet": "Unlikely",
    "wind": "Low chance (≤6%) of sustained tropical-storm-force winds; breezy conditions with occasional gusts possible if Delta tracks farther west.",
    "storm_surge": "Minor water-level rises (≤1 ft) and elevated surf/rip currents possible from long-period swells.",
    "rainfall": "Outer rainbands could bring 1–2 inches of rain late Thursday into Friday.",
    "other_hazards": "Dangerous rip currents and rough Gulf seas that could disrupt offshore operations and pilot transfers."
  }
}