{
  "cyclone": {
    "name": "DORIAN",
    "category": "Category 2",
    "current_location": "about 30 miles south of Cape Fear, North Carolina",
    "coordinates": "33.4N, 78.0W",
    "motion": {
      "direction": "NE",
      "speed": "10 mph"
    },
    "trajectory": "accelerating northeastward, skirting the North Carolina coast tonight then moving just east of southeastern Virginia on Friday before heading toward New England and Nova Scotia",
    "expected_landfall_location": "coast of North Carolina (near Cape Fear/Cape Lookout)",
    "expected_landfall_date": "2019-09-05",
    "hours_to_landfall": "12",
    "hours_to_offshore": "36",
    "hours_of_strike": "12"
  },
  "port": {
    "name": "Virginia, VA, Port of"
  },
  "weather_observation": {
    "within_uncertainty_cone": "Yes",
    "forecast_window": "5",
    "under_watch": "None",
    "under_warning": "Tropical Storm Warning; Storm Surge Warning",
    "watch_coast": "Hurricane Warning remains south of the NC/VA border; no watches in Virginia portion of coast",
    "warning_coast": "Tropical Storm Warning from NC/VA border to Fenwick Island DE, including lower Chesapeake Bay; Storm Surge Warning Duck NC to Poquoson VA including Hampton Roads",
    "impacted_coast": "Southeastern Virginia and the lower Chesapeake Bay coastline",
    "expected_closest_date_to_port": "2019-09-06",
    "expected_leaving_port_date": "2019-09-07",
    "closest_wind_data_location": "NORFOLK VA",
    "culmulative_wind_34kt": "30%",
    "culmulative_wind_50kt": "4%",
    "34kt_max": "31%",
    "time_to_34kt_max": "36",
    "time_to_34kt_non_zero": "0",
    "time_to_50kt_max": "24",
    "gale_probability": {
      "in 12h": "6%",
      "in 24h": "30%",
      "in 48h": "31%",
      "in 72h": "31%",
      "in 96h": "31%"
    },
    "first_hazard": "Arrival of tropical storm-force winds",
    "rain_fall_above_4_inch": "Likely (forecast 3-8 inches)",
    "storm_surge_above_3_feet": "Likely (forecast 2-4 ft, highest near 4 ft)",
    "wind": "Tropical-storm-force winds with gusts 45–55 mph possible Friday; low (4%) chance of 50-kt sustained winds",
    "storm_surge": "Inundation of 2–4 ft possible in Hampton Roads and lower Chesapeake Bay Friday during high tide",
    "rainfall": "Heavy rain bands could deliver 3–8 inches causing flash-flood risk in far southeast Virginia",
    "other_hazards": "Isolated tornadoes possible Friday; dangerous surf and rip currents preceding the storm"
  }
}