{
  "cyclone": {
    "name": "ELSA",
    "category": "Category 1",
    "current_location": "about 40 mi W of Barbados and 75 mi E of St. Vincent",
    "coordinates": "13.1N, 60.1W",
    "motion": {
      "direction": "WNW",
      "speed": "28 mph"
    },
    "trajectory": "tracking rapidly west-northwest across the eastern Caribbean, forecast to skirt the southern coast of Hispaniola Saturday, move near Jamaica Sunday, cross or graze Cuba Monday, then emerge in the eastern Gulf and curve toward the Florida peninsula and Big Bend Tuesday–Wednesday",
    "expected_landfall_location": "Florida Big Bend / northern Gulf Coast",
    "expected_landfall_date": "2021-07-07",
    "hours_to_landfall": "96",
    "hours_to_offshore": "120",
    "hours_of_strike": "18"
  },
  "port": {
    "name": "Canaveral Port District, FL"
  },
  "weather_observation": {
    "within_uncertainty_cone": "Yes",
    "forecast_window": "5",
    "under_watch": "None",
    "under_warning": "None",
    "watch_coast": "None issued for Florida at this time",
    "warning_coast": "None issued for Florida at this time",
    "impacted_coast": "Entire Florida peninsula, especially Gulf side, with outer bands possible along the east-central Atlantic coast including Port Canaveral",
    "expected_closest_date_to_port": "2021-07-06",
    "expected_leaving_port_date": "2021-07-07",
    "closest_wind_data_location": "COCOA BEACH FL",
    "culmulative_wind_34kt": "19%",
    "culmulative_wind_50kt": "3%",
    "34kt_max": "11%",
    "time_to_34kt_max": "108",
    "time_to_34kt_non_zero": "96",
    "time_to_50kt_max": "108",
    "gale_probability": {
      "in 12h": "0%",
      "in 24h": "0%",
      "in 48h": "0%",
      "in 72h": "0%",
      "in 96h": "8%"
    },
    "first_hazard": "Arrival of tropical storm-force winds",
    "rain_fall_above_4_inch": "No",
    "storm_surge_above_3_feet": "No",
    "wind": "Low to moderate chance (≤19%) of sustained 34–45 kt winds late Tuesday into early Wednesday; gusty squalls possible.",
    "storm_surge": "None expected along the Atlantic side of east-central Florida based on present track and intensity forecast.",
    "rainfall": "1–3 inches of rain with locally higher amounts up to 4 inches possible in outer rainbands.",
    "other_hazards": "Brief tornadoes or waterspouts in outer rainbands cannot be ruled out."
  }
}