{
  "cyclone": {
    "name": "FLORENCE",
    "category": "Category 2",
    "current_location": "about 625 mi (1005 km) SE of Bermuda",
    "coordinates": "24.9N, 58.9W",
    "motion": {
      "direction": "WNW",
      "speed": "9 mph"
    },
    "trajectory": "moving west-northwest across the southwest Atlantic and expected to turn northwest toward the North-Carolina/South-Carolina coast late Thursday",
    "expected_landfall_location": "coast of North Carolina (near Cape Fear-Cape Lookout area)",
    "expected_landfall_date": "2018-09-13",
    "hours_to_landfall": "80",
    "hours_to_offshore": "N/A",         		"hours_of_strike": "0"
  },
  "port": {
    "name": "New York, NY & NJ"
  },
  "weather_observation": {
    "within_uncertainty_cone": "No",
    "forecast_window": "5",
    "under_watch": "None",
    "under_warning": "None",
    "watch_coast": "None issued",
    "warning_coast": "None issued",
    "impacted_coast": "Greatest impact zone currently from the South Carolina coast northward to the southern Mid-Atlantic (NC/VA)",
    "expected_closest_date_to_port": "2018-09-14",
    "expected_leaving_port_date": "2018-09-15",
    "closest_wind_data_location": "NEWARK NJ",
    "culmulative_wind_34kt": "3%",
    "culmulative_wind_50kt": "<1%",
    "34kt_max": "2%",
    "time_to_34kt_max": "108",
    "time_to_34kt_non_zero": "96",
    "time_to_50kt_max": "120+",
    "gale_probability": {
      "in 12h": "0%",
      "in 24h": "0%",
      "in 48h": "0%",
      "in 72h": "0%",
      "in 96h": "1%"
    },
    "first_hazard": "Arrival of tropical storm-force winds",
    "rain_fall_above_4_inch": "Unlikely",
    "storm_surge_above_3_feet": "Unlikely",
    "wind": "Low (≤3%) chance of sustained tropical-storm-force winds late Friday into Saturday; otherwise breezy with gusts mainly below gale force.",
    "storm_surge": "None expected at this time for New York Harbor given track toward the Carolinas.",
    "rainfall": "Showers with locally heavy rain possible Friday night-Saturday as Florence’s remnant moisture gets drawn northward, but widespread 4-inch totals are not indicated.",
    "other_hazards": "Long-period swells and dangerous rip currents already affecting the New Jersey and Long Island beaches."
  }
}