{
  "cyclone": {
    "name": "FRED",
    "category": "Tropical Depression",
    "current_location": "about 90 miles south of Key West, Florida",
    "coordinates": "23.3N, 81.7W",
    "motion": {
      "direction": "WNW",
      "speed": "13 mph"
    },
    "trajectory": "moving west-northwest, then turning northwest and north toward the eastern Gulf of Mexico and Florida Panhandle",
    "expected_landfall_location": "Florida Panhandle (Apalachicola–Destin area)",
    "expected_landfall_date": "2021-08-16",
    "hours_to_landfall": "60",
    "hours_to_offshore": "24",
    "hours_of_strike": "36"
  },
  "port": {
    "name": "PortMiami, FL"
  },
  "weather_observation": {
    "within_uncertainty_cone": "No",
    "forecast_window": "5",
    "under_watch": "None",
    "under_warning": "None",
    "watch_coast": "Florida Keys west of the Seven Mile Bridge to the Dry Tortugas",
    "warning_coast": "Florida Keys west of the Seven Mile Bridge to the Dry Tortugas",
    "impacted_coast": "Florida Keys, southern Florida peninsula, eastern Gulf Coast, Florida Panhandle, northern Gulf Coast of Alabama–Mississippi",
    "expected_closest_date_to_port": "2021-08-14",
    "expected_leaving_port_date": "2021-08-15",
    "closest_wind_data_location": "MARATHON FL",
    "culmulative_wind_34kt": "5%",
    "culmulative_wind_50kt": "0%",
    "34kt_max": "5%",
    "time_to_34kt_max": "24",
    "time_to_34kt_non_zero": "0",
    "time_to_50kt_max": "",
    "gale_probability": {
      "in 12h": "3%",
      "in 24h": "2%",
      "in 48h": "0%",
      "in 72h": "0%",
      "in 96h": "0%"
    },
    "first_hazard": "Start of heavy rainfall",
    "rain_fall_above_4_inch": "Yes",
    "storm_surge_above_3_feet": "No",
    "wind": "Low (≈5%) chance of brief tropical-storm-force gusts; sustained winds likely remain below 34 kt at PortMiami.",
    "storm_surge": "None expected on the Atlantic side; surge confined mainly to the Gulf Coast.",
    "rainfall": "3–5 inches with locally higher amounts up to 8 inches possible, producing urban and small-stream flooding around Miami-Dade County.",
    "other_hazards": "Isolated tornadoes possible Saturday–Sunday; rough seas and long-period swells may affect vessel traffic near the port."
  }
}