{
  "cyclone": {
    "name": "HERMINE",
    "category": "Tropical Depression",
    "current_location": "about 345 miles W of Key West, Florida",
    "coordinates": "24.4N, 87.3W",
    "motion": {
      "direction": "NW",
      "speed": "5 mph"
    },
    "trajectory": "forecast to turn NNW tonight and then NNE toward the northeast Gulf coast of Florida",
    "expected_landfall_location": "Florida Big Bend coast between the Anclote River and Indian Pass",
    "expected_landfall_date": "2016-09-01",
    "hours_to_landfall": "48",
    "hours_to_offshore": "24",
    "hours_of_strike": "0"
  },
  "port": {
    "name": "Plaquemines Port District, LA"
  },
  "weather_observation": {
    "within_uncertainty_cone": "No",
    "forecast_window": "5",
    "under_watch": "None",
    "under_warning": "None",
    "watch_coast": "Hurricane Watch from Anclote River to Indian Pass FL; Tropical Storm Watch west of Indian Pass to the Walton/Bay County line",
    "warning_coast": "None in effect (only watches issued so far)",
    "impacted_coast": "Florida Gulf Coast, especially the Big Bend region; tropical-storm-force wind field may extend westward to the FL/AL border",
    "expected_closest_date_to_port": "2016-08-31",
    "expected_leaving_port_date": "2016-09-01",
    "closest_wind_data_location": "BURAS LA",
    "culmulative_wind_34kt": "3%",
    "culmulative_wind_50kt": "<1%",
    "34kt_max": "3%",
    "time_to_34kt_max": "48",
    "time_to_34kt_non_zero": "24",
    "time_to_50kt_max": "",
    "gale_probability": {
      "in 12h": "0%",
      "in 24h": "1%",
      "in 48h": "3%",
      "in 72h": "3%",
      "in 96h": "3%"
    },
    "first_hazard": "None expected at Plaquemines Port District, LA",
    "rain_fall_above_4_inch": "Unlikely",
    "storm_surge_above_3_feet": "Unlikely",
    "wind": "Breezy conditions possible, but the chance of sustained tropical-storm-force winds is only 3%",
    "storm_surge": "None expected for Plaquemines Parish; surge threat is confined to Florida Big Bend",
    "rainfall": "Only scattered showers expected; heavy core rainfall remains well east of Louisiana",
    "other_hazards": "None anticipated that would significantly disrupt port operations"
  }
}