{
  "cyclone": {
    "name": "IAN",
    "category": "Tropical Depression",
    "current_location": "about 430 mi ESE of Kingston, Jamaica",
    "coordinates": "14.7N, 71.3W",
    "motion": {
      "direction": "WNW",
      "speed": "15 mph"
    },
    "trajectory": "moving westward tonight, then turning northwest and north-northwest; forecast to pass south of Jamaica Sunday, approach the Cayman Islands late Sunday–early Monday, move over or near western Cuba Monday night, then track northward in the east-central Gulf toward the Florida Gulf Coast mid-week",
    "expected_landfall_location": "Florida Gulf Coast (around the Tampa Bay vicinity)",
    "expected_landfall_date": "2022-09-28",
    "hours_to_landfall": "120",
    "hours_to_offshore": "132",
    "hours_of_strike": "18"
  },
  "port": {
    "name": "Port Everglades, FL"
  },
  "weather_observation": {
    "within_uncertainty_cone": "No",
    "forecast_window": "5",
    "under_watch": "None",
    "under_warning": "None",
    "watch_coast": "Hurricane Watch for Cayman Islands; Tropical Storm Watch for Jamaica",
    "warning_coast": "None currently in effect",
    "impacted_coast": "Central and western Caribbean, Cayman Islands, western Cuba, Florida Gulf Coast, portions of the Florida Peninsula",
    "expected_closest_date_to_port": "2022-09-28",
    "expected_leaving_port_date": "2022-09-29",
    "closest_wind_data_location": "FT LAUDERDALE FL",
    "culmulative_wind_34kt": "37%",
    "culmulative_wind_50kt": "10%",
    "34kt_max": "37%",
    "time_to_34kt_max": "120",
    "time_to_34kt_non_zero": "72",
    "time_to_50kt_max": "120",
    "gale_probability": {
      "in 12h": "0%",
      "in 24h": "0%",
      "in 48h": "0%",
      "in 72h": "2%",
      "in 96h": "20%"
    },
    "first_hazard": "Start of heavy rainfall",
    "rain_fall_above_4_inch": "Possible but uncertain (limited urban flood risk noted)",
    "storm_surge_above_3_feet": "Unlikely",
    "wind": "Tropical-storm-force winds are possible mid-week with peak 34-kt probability ~37%",
    "storm_surge": "No significant surge currently forecast for the southeast Florida Atlantic coast",
    "rainfall": "Bands of heavy rain could begin Monday; totals may approach 4 inches with localized flooding",
    "other_hazards": "Dangerous rip currents and rough surf mid-week"
  }
}