{
  "cyclone": {
    "name": "IDALIA",
    "category": "Tropical Storm",
    "current_location": "about 95 mi ESE of Cozumel, Mexico",
    "coordinates": "20.1N, 85.5W",
    "motion": {
      "direction": "NE",
      "speed": "3 mph"
    },
    "trajectory": "accelerating north-northeast through the eastern Gulf of Mexico toward the northeast Gulf Coast of Florida (Big Bend/Tampa Bay area)",
    "expected_landfall_location": "Florida Big Bend coast, roughly Cedar Key–Aucilla River area",
    "expected_landfall_date": "2023-08-30",
    "hours_to_landfall": "56",
    "hours_to_offshore": "48",
    "hours_of_strike": "18"
  },
  "port": {
    "name": "Manatee County Port, FL"
  },
  "weather_observation": {
    "within_uncertainty_cone": "Yes",
    "forecast_window": "5",
    "under_watch": "Hurricane Watch",
    "under_warning": "None",
    "watch_coast": "Englewood to Indian Pass FL, including Tampa Bay",
    "warning_coast": "None",
    "impacted_coast": "Florida Gulf Coast from Chokoloskee northward to Indian Pass, including Tampa Bay and the Big Bend region",
    "expected_closest_date_to_port": "2023-08-29",
    "expected_leaving_port_date": "2023-08-30",
    "closest_wind_data_location": "TAMPA FL",
    "culmulative_wind_34kt": "71%",
    "culmulative_wind_50kt": "32%",
    "34kt_max": "47%",
    "time_to_34kt_max": "72",
    "time_to_34kt_non_zero": "36",
    "time_to_50kt_max": "72",
    "gale_probability": {
      "in 12h": "0%",
      "in 24h": "0%",
      "in 48h": "22%",
      "in 72h": "47%",
      "in 96h": "0%"
    },
    "first_hazard": "Start of storm surge",
    "rain_fall_above_4_inch": "Yes",
    "storm_surge_above_3_feet": "Yes",
    "wind": "Tropical-storm-force winds likely (71% chance of ≥34 kt, up to 32% chance of ≥50 kt) with the possibility of hurricane-force gusts if Idalia intensifies just offshore.",
    "storm_surge": "Storm surge of 3–5 ft above ground level possible in Tampa Bay including Port Manatee.",
    "rainfall": "3–6 inches of rain with local maxima up to 10 inches could produce flash and urban flooding around the port.",
    "other_hazards": "Brief tornadoes in outer rainbands, dangerous seas, and heavy wave action in lower Tampa Bay."
  }
}