{
  "cyclone": {
    "name": "IDALIA",
    "category": "Category 1",
    "current_location": "about 85 mi north of the western tip of Cuba",
    "coordinates": "23.1N, 85.0W",
    "motion": {
      "direction": "N",
      "speed": "14 mph"
    },
    "trajectory": "moving north, then accelerating north-northeast toward the Florida Big Bend, then across southeast Georgia and near the South Carolina coast",
    "expected_landfall_location": "Florida Big Bend (near Cedar Key/Indian Pass area)",
    "expected_landfall_date": "2023-08-30",
    "hours_to_landfall": "24",
    "hours_to_offshore": "60",
    "hours_of_strike": "12"
  },
  "port": {
    "name": "Port of Charleston, SC"
  },
  "weather_observation": {
    "within_uncertainty_cone": "Yes",
    "forecast_window": "5",
    "under_watch": "Tropical Storm Watch",
    "under_warning": "None",
    "watch_coast": "Altamaha Sound, GA to South Santee River, SC",
    "warning_coast": "None for South Carolina coast as of Advisory 11",
    "impacted_coast": "Florida Gulf Coast (Englewood to Indian Pass), southeast Georgia and the South Carolina coast through South Santee River",
    "expected_closest_date_to_port": "2023-08-31",
    "expected_leaving_port_date": "2023-08-31",
    "closest_wind_data_location": "CHARLESTON SC",
    "culmulative_wind_34kt": "69%",
    "culmulative_wind_50kt": "26%",
    "34kt_max": "69%",
    "time_to_34kt_max": "72",
    "time_to_34kt_non_zero": "36",
    "time_to_50kt_max": "72",
    "gale_probability": {
      "in 12h": "0%",
      "in 24h": "0%",
      "in 48h": "50%",
      "in 72h": "7%",
      "in 96h": "0%"
    },
    "first_hazard": "Start of heavy rainfall",
    "rain_fall_above_4_inch": "Yes",
    "storm_surge_above_3_feet": "Yes",
    "wind": "Tropical-storm-force winds likely Wednesday night into early Thursday; 69 % chance of ≥34 kt, 26 % chance of ≥50 kt, and 6 % chance of hurricane-force gusts.",
    "storm_surge": "2–4 ft of inundation possible for the mouth of the St. Mary’s River to South Santee River, including Charleston Harbor.",
    "rainfall": "4–8 in of rain possible across eastern South Carolina, producing flash and urban flooding around Charleston.",
    "other_hazards": "Isolated tornadoes in outer rainbands; dangerous surf and rip currents ahead of the storm."
  }
}