{
  "cyclone": {
    "name": "MICHAEL",
    "category": "Category 1",
    "current_location": "about 455 miles south of Panama City, Florida",
    "coordinates": "23.6N, 85.7W",
    "motion": {
      "direction": "NNW",
      "speed": "12 mph"
    },
    "trajectory": "moving north-northwest across the east-central Gulf, then turning northeast toward the Florida Panhandle and inland across the south-eastern U.S.",
    "expected_landfall_location": "Florida Panhandle / Big Bend coast (near Panama City – Apalachicola)",
    "expected_landfall_date": "2018-10-10",
    "hours_to_landfall": "36",
    "hours_to_offshore": "24",
    "hours_of_strike": "12"
  },
  "port": {
    "name": "Port of Pascagoula, MS"
  },
  "weather_observation": {
    "within_uncertainty_cone": "No",                 
    "forecast_window":"5",
    "under_watch": "Tropical Storm Watch",
    "under_warning": "None",
    "watch_coast": "Mississippi/Alabama border westward to the Mouth of the Pearl River, including Pascagoula",
    "warning_coast": "none for Mississippi coast; hurricane & surge warnings confined east of Alabama/Florida border",
    "impacted_coast": "eastern Louisiana through Mississippi and Alabama coasts subject to outer rain bands and modest surge; primary impact zone Florida Panhandle",
    "expected_closest_date_to_port": "2018-10-10",
    "expected_leaving_port_date": "2018-10-11",
    "closest_wind_data_location":"GULFPORT MS",
    "culmulative_wind_34kt":"10%",
    "culmulative_wind_50kt":"<3%",
    "34kt_max":"10%",
    "time_to_34kt_max":"~48 h",
    "time_to_34kt_non_zero":"~12 h",
    "time_to_50kt_max":"N/A",
    "gale_probability": {
      "in 12h": "0-2%",
      "in 24h": "4%",
      "in 48h": "10%",
      "in 72h": "11%",
      "in 96h": "11%"
    },
    "first_hazard":"Arrival of tropical storm-force winds",
    "rain_fall_above_4_inch":"Unlikely",
    "storm_surge_above_3_feet":"No (2–3 ft possible at most)",
    "wind":"Outer bands could bring sustained 25–35 kt (30–40 mph) winds with higher gusts late Tue night through Wed evening",
    "storm_surge":"Minor surge of 2–3 ft possible on open coast and in bays; less inside the port’s protected channel",
    "rainfall":"1–3 inches possible in bands; flash-flood risk low",
    "other_hazards": "Brief squalls causing sudden wind shifts and reduced visibility; elevated seas and rip currents along approaches"
  }
}