{
  "cyclone": {
    "name": "NESTOR",
    "category": "Tropical Storm (not yet on SSHS scale)",
    "current_location": "about 155 mi E of Tampico, Mexico",
    "coordinates": "22.6N, 95.5W",
    "motion": {
      "direction": "N (turning NE later today)",
      "speed": "7 mph"
    },
    "trajectory": "accelerating northeastward, expected to cross the northeastern Gulf of Mexico, make landfall along the Florida Panhandle Friday evening, then sweep across GA/SC and exit into the western Atlantic",
    "expected_landfall_location": "Florida Panhandle near Apalachicola–St. Marks",
    "expected_landfall_date": "2019-10-18",
    "hours_to_landfall": "33",
    "hours_to_offshore": "60",
    "hours_of_strike": "12"
  },
  "port": {
    "name": "Jacksonville, FL"
  },
  "weather_observation": {
    "within_uncertainty_cone": "Yes",
    "forecast_window": "5",
    "under_watch": "None",
    "under_warning": "None",
    "watch_coast": "East of the Ochlockonee River to Yankeetown, FL (Big Bend Gulf coast)",
    "warning_coast": "Mouth of Pearl River LA eastward to the MS/AL border and to the Ochlockonee River, FL; also Grand Isle LA",
    "impacted_coast": "Northern Gulf Coast from Louisiana to Florida Panhandle, then inland across Georgia and the Carolinas to the Mid-Atlantic seaboard",
    "expected_closest_date_to_port": "2019-10-19",
    "expected_leaving_port_date": "2019-10-19",
    "closest_wind_data_location": "JACKSONVILLE",
    "culmulative_wind_34kt": "24%",
    "culmulative_wind_50kt": "3%",
    "34kt_max": "14%",
    "time_to_34kt_max": "48",
    "time_to_34kt_non_zero": "36",
    "time_to_50kt_max": "48",
    "gale_probability": {
      "in 12h": "0%",
      "in 24h": "0%",
      "in 48h": "10%",
      "in 72h": "24%",
      "in 96h": "24%"
    },
    "first_hazard": "Start of heavy rainfall",
    "rain_fall_above_4_inch": "Possible (isolated 5-inch totals in forecast)",
    "storm_surge_above_3_feet": "Unlikely on Atlantic side",
    "wind": "Tropical-storm-force gusts (34 kt) possible Saturday; overall 24 % cumulative risk",
    "storm_surge": "None expected for Jacksonville’s Atlantic coast; surge watch confined to Gulf side of FL",
    "rainfall": "2–4 inches with locally higher amounts Saturday",
    "other_hazards": "Brief tornadoes cannot be ruled out in outer rain bands as system passes"
  }
}